[
	{
		"sure": "2",
		"sonuc": 1334,
		"deger": 4784,
		"toplam": 41660406,
		"harf": "الم"
	},
	{
		"sure": "3",
		"sonuc": 4742,
		"deger": 4784,
		"toplam": 23790790,
		"harf": "الم"
	},
	{
		"sure": "7",
		"sonuc": 3319,
		"deger": 6373,
		"toplam": 22895135,
		"harf": "المص"
	},
	{
		"sure": "10",
		"sonuc": 1690,
		"deger": 4764,
		"toplam": 12040318,
		"harf": "الر"
	},
	{
		"sure": "11",
		"sonuc": 916,
		"deger": 4764,
		"toplam": 12387316,
		"harf": "الر"
	},
	{
		"sure": "12",
		"sonuc": 4087,
		"deger": 4764,
		"toplam": 11599663,
		"harf": "الر"
	},
	{
		"sure": "13",
		"sonuc": 3346,
		"deger": 6369,
		"toplam": 5608066,
		"harf": "المر"
	},
	{
		"sure": "14",
		"sonuc": 3634,
		"deger": 4764,
		"toplam": 5606098,
		"harf": "الر"
	},
	{
		"sure": "15",
		"sonuc": 3734,
		"deger": 4764,
		"toplam": 4577174,
		"harf": "الر"
	},
	{
		"sure": "19",
		"sonuc": 6237,
		"deger": 8002,
		"toplam": 6263801,
		"harf": "كهيعص"
	},
	{
		"sure": "20",
		"sonuc": 503,
		"deger": 3198,
		"toplam": 8587133,
		"harf": "طه"
	},
	{
		"sure": "26",
		"sonuc": 4317,
		"deger": 4783,
		"toplam": 8953310,
		"harf": "طسم"
	},
	{
		"sure": "27",
		"sonuc": 1409,
		"deger": 3178,
		"toplam": 7596829,
		"harf": "طس"
	},
	{
		"sure": "28",
		"sonuc": 715,
		"deger": 4783,
		"toplam": 9404093,
		"harf": "طسم"
	},
	{
		"sure": "29",
		"sonuc": 2914,
		"deger": 4784,
		"toplam": 6848818,
		"harf": "الم"
	},
	{
		"sure": "30",
		"sonuc": 3603,
		"deger": 4784,
		"toplam": 5505203,
		"harf": "الم"
	},
	{
		"sure": "31",
		"sonuc": 3099,
		"deger": 4784,
		"toplam": 3457147,
		"harf": "الم"
	},
	{
		"sure": "32",
		"sonuc": 1894,
		"deger": 4784,
		"toplam": 2480006,
		"harf": "الم"
	},
	{
		"sure": "36",
		"sonuc": 2789,
		"deger": 3197,
		"toplam": 4878214,
		"harf": "يس"
	},
	{
		"sure": "38",
		"sonuc": 54,
		"deger": 1589,
		"toplam": 4868750,
		"harf": "ص"
	},
	{
		"sure": "40",
		"sonuc": 1023,
		"deger": 3186,
		"toplam": 8106207,
		"harf": "حم"
	},
	{
		"sure": "41",
		"sonuc": 895,
		"deger": 3186,
		"toplam": 5327887,
		"harf": "حم"
	},
	{
		"sure": "42",
		"sonuc": 2711,
		"deger": 3186,
		"toplam": 5575025,
		"harf": "حم"
	},
	{
		"sure": "43",
		"sonuc": 1911,
		"deger": 3186,
		"toplam": 5723967,
		"harf": "حم"
	},
	{
		"sure": "44",
		"sonuc": 3100,
		"deger": 3186,
		"toplam": 2338438,
		"harf": "حم"
	},
	{
		"sure": "45",
		"sonuc": 2018,
		"deger": 3186,
		"toplam": 3309086,
		"harf": "حم"
	},
	{
		"sure": "46",
		"sonuc": 676,
		"deger": 3186,
		"toplam": 4241242,
		"harf": "حم"
	},
	{
		"sure": "50",
		"sonuc": 1489,
		"deger": 1602,
		"toplam": 2385265,
		"harf": "ق"
	},
	{
		"sure": "68",
		"sonuc": 163,
		"deger": 1606,
		"toplam": 2051025,
		"harf": "ن"
	}
]