[
	{
		"sure": 286,
		"sonuc": -8535407,
		"deger": " 59",
		"harf": "الم",
		"aharf": -144668
	},
	{
		"sure": 200,
		"sonuc": -4806228,
		"deger": " 59",
		"harf": "الم",
		"aharf": -81461
	},
	{
		"sure": 206,
		"sonuc": -4566471,
		"deger": " 73",
		"harf": "المص",
		"aharf": -62554
	},
	{
		"sure": 109,
		"sonuc": -2523155,
		"deger": " 39",
		"harf": "الر",
		"aharf": -64696
	},
	{
		"sure": 123,
		"sonuc": -2665142,
		"deger": " 39",
		"harf": "الر",
		"aharf": -68337
	},
	{
		"sure": 111,
		"sonuc": -2462537,
		"deger": " 39",
		"harf": "الر",
		"aharf": -63142
	},
	{
		"sure": 43,
		"sonuc": -1184848,
		"deger": " 69",
		"harf": "المر",
		"aharf": -17172
	},
	{
		"sure": 52,
		"sonuc": -1133838,
		"deger": " 39",
		"harf": "الر",
		"aharf": -29073
	},
	{
		"sure": 99,
		"sonuc": -805815,
		"deger": " 39",
		"harf": "الر",
		"aharf": -20662
	},
	{
		"sure": 98,
		"sonuc": -1275008,
		"deger": " 127",
		"harf": "كهيعص",
		"aharf": -10039
	},
	{
		"sure": 135,
		"sonuc": -1778063,
		"deger": " 48",
		"harf": "طه",
		"aharf": -37043
	},
	{
		"sure": 227,
		"sonuc": -1577106,
		"deger": " 58",
		"harf": "طسم",
		"aharf": -27191
	},
	{
		"sure": 93,
		"sonuc": -1554339,
		"deger": " 28",
		"harf": "طس",
		"aharf": -55512
	},
	{
		"sure": 88,
		"sonuc": -1968553,
		"deger": " 58",
		"harf": "طسم",
		"aharf": -33941
	},
	{
		"sure": 69,
		"sonuc": -1319516,
		"deger": " 59",
		"harf": "الم",
		"aharf": -22365
	},
	{
		"sure": 60,
		"sonuc": -1100291,
		"deger": " 59",
		"harf": "الم",
		"aharf": -18649
	},
	{
		"sure": 34,
		"sonuc": -754829,
		"deger": " 59",
		"harf": "الم",
		"aharf": -12794
	},
	{
		"sure": 30,
		"sonuc": -497677,
		"deger": " 59",
		"harf": "الم",
		"aharf": -8435
	},
	{
		"sure": 83,
		"sonuc": -938204,
		"deger": " 47",
		"harf": "يس",
		"aharf": -19962
	},
	{
		"sure": 88,
		"sonuc": -944372,
		"deger": " 14",
		"harf": "ص",
		"aharf": -67455
	},
	{
		"sure": 85,
		"sonuc": -1664037,
		"deger": " 36",
		"harf": "حم",
		"aharf": -46223
	},
	{
		"sure": 54,
		"sonuc": -1078250,
		"deger": " 36",
		"harf": "حم",
		"aharf": -29951
	},
	{
		"sure": 53,
		"sonuc": -1176614,
		"deger": " 36",
		"harf": "حم",
		"aharf": -32684
	},
	{
		"sure": 89,
		"sonuc": -1083604,
		"deger": " 36",
		"harf": "حم",
		"aharf": -30100
	},
	{
		"sure": 59,
		"sonuc": -414161,
		"deger": " 36",
		"harf": "حم",
		"aharf": -11504
	},
	{
		"sure": 37,
		"sonuc": -656233,
		"deger": " 36",
		"harf": "حم",
		"aharf": -18229
	},
	{
		"sure": 35,
		"sonuc": -890721,
		"deger": " 36",
		"harf": "حم",
		"aharf": -24742
	},
	{
		"sure": 45,
		"sonuc": -477551,
		"deger": " 27",
		"harf": "ق",
		"aharf": -17687
	},
	{
		"sure": 52,
		"sonuc": -359197,
		"deger": " 31",
		"harf": "ن",
		"aharf": -11587
	}
]